userextensions/__init__.py
userextensions/admin.py
userextensions/apps.py
userextensions/decorators.py
userextensions/forms.py
userextensions/middleware.py
userextensions/mixins.py
userextensions/models.py
userextensions/signals.py
userextensions/urls.py
userextensions/management/__init__.py
userextensions/management/commands/__init__.py
userextensions/management/commands/add_service_account.py
userextensions/migrations/0001_initial.py
userextensions/migrations/0002_userpreference_start_page.py
userextensions/migrations/0003_auto_20200117_2153.py
userextensions/migrations/0004_serviceaccount_serviceaccounttokenhistory.py
userextensions/migrations/0005_auto_20201114_0548.py
userextensions/migrations/0006_auto_20210507_1831.py
userextensions/migrations/0007_auto_20220807_2104.py
userextensions/migrations/0008_alter_serviceaccount_id_and_more.py
userextensions/migrations/__init__.py
userextensions/templates/userextensions/userextensions_base.htm
userextensions/templates/userextensions/ajax/get_token_history_for_srv_acct.htm
userextensions/templates/userextensions/ajax/get_users_per_group.htm
userextensions/templates/userextensions/ajax/show_srv_acct_token.htm
userextensions/templates/userextensions/custom/create_custom_service_account.htm
userextensions/templates/userextensions/custom/manage_service_accounts.html
userextensions/templates/userextensions/detail/detail_user.html
userextensions/templates/userextensions/form/edit_favorite.htm
userextensions/templates/userextensions/snippets/user_extensions_nav_menu.htm
userextensions/templates/userextensions/snippets/user_theme.htm
userextensions/templates/userextensions/table/table_favorites.htm
userextensions/templates/userextensions/table/table_recents.htm
userextensions/templatetags/__init__.py
userextensions/templatetags/userextension_tags.py
userextensions/views/__init__.py
userextensions/views/action.py
userextensions/views/ajax.py
userextensions/views/gui.py
django_userextensions-0.3.3.dist-info/LICENSE
django_userextensions-0.3.3.dist-info/METADATA
django_userextensions-0.3.3.dist-info/WHEEL
django_userextensions-0.3.3.dist-info/top_level.txt
django_userextensions-0.3.3.dist-info/RECORD
