Metadata-Version: 2.1
Name: django-userextensions
Version: 0.3.3
Summary: A user extension module for django
Home-page: https://github.com/davidslusser/django-userextensions
Download-URL: https://github.com/davidslusser/django-userextensions/archive/0.3.3.tar.gz
Author: David Slusser
Author-email: dbslusser@gmail.com
License: GPL-3.0
Keywords: django,helpers,extension,user,profile
Classifier: Environment :: Web Environment
Classifier: Intended Audience :: Developers
Classifier: Operating System :: OS Independent
Classifier: Programming Language :: Python :: 3
Classifier: Framework :: Django :: 4.2
Classifier: Topic :: Internet :: WWW/HTTP
Classifier: Topic :: Internet :: WWW/HTTP :: Dynamic Content
Classifier: Topic :: Software Development :: Libraries :: Python Modules
License-File: LICENSE
Requires-Dist: Django >=4.2
Requires-Dist: django-braces
Requires-Dist: django-handyhelpers >=0.3
